nonebot_plugin_bili_fav_watcher/__init__.py
nonebot_plugin_bili_fav_watcher/command.py
nonebot_plugin_bili_fav_watcher/config.py
nonebot_plugin_bili_fav_watcher/core.py
nonebot_plugin_bili_fav_watcher/local.py
nonebot_plugin_bili_fav_watcher/util.py
nonebot_plugin_bili_fav_watcher-0.1.12.dist-info/METADATA
nonebot_plugin_bili_fav_watcher-0.1.12.dist-info/WHEEL
nonebot_plugin_bili_fav_watcher-0.1.12.dist-info/RECORD
