Metadata-Version: 2.1
Name: nonebot-plugin-bili-fav-watcher
Version: 0.1.12
Summary: A Bilibili user video favorites monitor
Home-page: https://github.com/kawaiior/nonebot-plugin-bili-fav-watcher
Author: SakanaVollerei
Author-email: kawaiiorv@gmail.com
Requires-Python: >=3.8
Classifier: Programming Language :: Python :: 3
Classifier: Programming Language :: Python :: 3.8
Classifier: Programming Language :: Python :: 3.9
Classifier: Programming Language :: Python :: 3.10
Classifier: Programming Language :: Python :: 3.11
Classifier: Programming Language :: Python :: 3.12
Requires-Dist: bilibili-api-python (>=17.3.0)
Requires-Dist: nonebot-adapter-onebot (>=2.0.0-beta.1)
Requires-Dist: nonebot-plugin-apscheduler (>=0.3.0)
Requires-Dist: nonebot-plugin-localstore (>=0.6.0)
Requires-Dist: nonebot2 (>=2.2.0)
Project-URL: Repository, https://github.com/kawaiior/nonebot-plugin-bili-fav-watcher
